release_by_changelog/__init__.py
release_by_changelog/app.py
release_by_changelog/logging.py
release_by_changelog/main.py
release_by_changelog/py.typed
release_by_changelog/typings_.py
release_by_changelog/cmds/__init__.py
release_by_changelog/cmds/_release.py
release_by_changelog/cmds/release.py
release_by_changelog/services/__init__.py
release_by_changelog/services/release.py
release_by_changelog-0.2.3.dist-info/METADATA
release_by_changelog-0.2.3.dist-info/WHEEL
release_by_changelog-0.2.3.dist-info/entry_points.txt
release_by_changelog-0.2.3.dist-info/licenses/AUTHORS.rst
release_by_changelog-0.2.3.dist-info/licenses/LICENCE
release_by_changelog-0.2.3.dist-info/RECORD
