Metadata-Version: 2.3
Name: release_by_changelog
Version: 0.2.3
Summary: Release a new version of a software based on CHANGELOG.md file.
Project-URL: Bug Tracker, https://lab.frogg.it/swepy/release-by-changelog/-/issues
Project-URL: Homepage, https://lab.frogg.it/swepy/release-by-changelog
Author-email: Dorian Turba <releasebychangelog.rjsts@simplelogin.com>
License-File: AUTHORS.rst
License-File: LICENCE
Classifier: Development Status :: 3 - Alpha
Classifier: License :: OSI Approved :: MIT License
Classifier: Operating System :: OS Independent
Classifier: Programming Language :: Python :: 3
Classifier: Programming Language :: Python :: 3.11
Classifier: Programming Language :: Python :: 3.12
Classifier: Typing :: Typed
Requires-Python: >=3.11
Requires-Dist: python-gitlab
Requires-Dist: typer[all]
Provides-Extra: all
Requires-Dist: bump-my-version; extra == 'all'
Requires-Dist: coverage; extra == 'all'
Requires-Dist: pip-tools; extra == 'all'
Requires-Dist: pre-commit; extra == 'all'
Requires-Dist: pyright; extra == 'all'
Requires-Dist: pytest; extra == 'all'
Requires-Dist: pytest-mock; extra == 'all'
Requires-Dist: ruff>=0.3.3; extra == 'all'
Requires-Dist: toml-sort; extra == 'all'
Provides-Extra: dev
Requires-Dist: bump-my-version; extra == 'dev'
Requires-Dist: pip-tools; extra == 'dev'
Provides-Extra: quality
Requires-Dist: pre-commit; extra == 'quality'
Requires-Dist: pyright; extra == 'quality'
Requires-Dist: ruff>=0.3.3; extra == 'quality'
Requires-Dist: toml-sort; extra == 'quality'
Provides-Extra: test
Requires-Dist: coverage; extra == 'test'
Requires-Dist: pytest; extra == 'test'
Requires-Dist: pytest-mock; extra == 'test'
